[
    {
        "fullType": "Base.Belly_Turtleneck",
        "price": 500.0
    },
    {
        "fullType": "Base.Adidas_Pad_Jacket_ON",
        "price": 500.0
    },
    {
        "fullType": "Base.BellyButton_RingGoldRuby",
        "price": 1000.0
    },
    {
        "fullType": "Base.WildGarlicCataplasm",
        "price": 200.0
    },
    {
        "fullType": "Base.ANA_Classic_ON",
        "price": 500.0
    },
    {
        "fullType": "Base.PipeBomb",
        "price": 500.0
    },
    {
        "fullType": "Base.MakeupEyeshadow",
        "price": 1000.0
    },
    {
        "fullType": "Base.Hat_GasMask",
        "price": 1000.0
    },
    {
        "fullType": "Base.Shirt_Scrubs",
        "price": 500.0
    },
    {
        "fullType": "Base.ToiletTissue",
        "price": 500.0
    },
    {
        "fullType": "Base.Mov_BinRound",
        "price": 1500.0
    },
    {
        "fullType": "Base.PlasticCupWater",
        "price": 500.0
    },
    {
        "fullType": "Base.LightBulbOrange",
        "price": 500.0
    },
    {
        "fullType": "Base.Heather_Bomber",
        "price": 500.0
    },
    {
        "fullType": "Base.WaterBottleFull",
        "price": 500.0
    },
    {
        "fullType": "Base.Umbrella",
        "price": 2000.0
    },
    {
        "fullType": "Base.NormalGasTank1",
        "price": 300.0
    },
    {
        "fullType": "Base.BarbedWire",
        "price": 500.0
    }
]